
{
  "expression_function_GroupName_functionname": {
    "caption": "The label of the screenshot",
    "img": "file without extension in expression help image folder - takes precedence over algfile",
    "alg_img": "file without extension in algorithm img folder" },

  "expression_function_GeometryGroup_bounds": {
    "caption": "Black lines represent the bounding boxes of each polygon feature",
    "img": "",
    "alg_img": "bounding_box" },
  "expression_function_GeometryGroup_buffer": {
    "caption": "Buffer (in yellow) of points, line, polygon with positive buffer, and polygon with negative buffer",
    "img": "",
    "alg_img":"buffer" },
  "expression_function_GeometryGroup_buffer_by_m": {
    "caption": "Buffering line features using the m value on the vertices",
    "img": "",
    "alg_img":"variable_buffer_m" },
  "expression_function_GeometryGroup_centroid": {
    "caption": "The red stars represent the centroids of the features of the input layer.",
    "img": "",
    "alg_img":"centroids.png" },
  "expression_function_GeometryGroup_rotate": {
    "caption": "Rotating features",
    "img": "rotate",
    "alg_img":"" },
  "expression_function_GeometryGroup_tapered_buffer": {
    "caption": "Tapered buffer on line features",
    "img": "",
    "alg_img":"tapered_buffer" },
  "expression_function_GeometryGroup_translate": {
    "caption": "Translating features",
    "img": "",
    "alg_img":"translate_geometry" }
}
